openai_mcp_agents/__init__.py
openai_mcp_agents/mcp_agent.py
openai_mcp_agents/py.typed
openai_mcp_agents/tools.py
openai_mcp_agents-0.1.0.dist-info/METADATA
openai_mcp_agents-0.1.0.dist-info/WHEEL
openai_mcp_agents-0.1.0.dist-info/licenses/LICENSE
openai_mcp_agents-0.1.0.dist-info/RECORD
