Metadata-Version: 2.4
Name: openai-mcp-agents
Version: 0.1.0
Summary: SDK for integrating Model Context Protocol (MCP) into OpenAI Agents
Project-URL: Homepage, https://github.com/madroidmaq/openai-mcp-agents
Project-URL: Repository, https://github.com/madroidmaq/openai-mcp-agents.git
Project-URL: Issues, https://github.com/madroidmaq/openai-mcp-agents/issues
Project-URL: Changelog, https://github.com/madroidmaq/openai-mcp-agents/blob/main/CHANGELOG.md
Author-email: madroid <madroidmaq@gmail.com>
License: Apache-2.0
License-File: LICENSE
Keywords: agents,mcp,model-context-protocol,openai
Classifier: Development Status :: 4 - Beta
Classifier: Intended Audience :: Developers
Classifier: License :: OSI Approved :: Apache Software License
Classifier: Programming Language :: Python :: 3
Classifier: Programming Language :: Python :: 3.11
Classifier: Topic :: Scientific/Engineering :: Artificial Intelligence
Classifier: Topic :: Software Development :: Libraries :: Python Modules
Requires-Python: >=3.11
Requires-Dist: mcp>=1.4.1
Requires-Dist: openai-agents>=0.0.7
Provides-Extra: dev
Requires-Dist: black>=23.0.0; extra == 'dev'
Requires-Dist: coverage>=7.0.0; extra == 'dev'
Requires-Dist: flake8>=6.0.0; extra == 'dev'
Requires-Dist: isort>=5.12.0; extra == 'dev'
Requires-Dist: mypy>=1.0.0; extra == 'dev'
Requires-Dist: pytest-asyncio>=0.21.0; extra == 'dev'
Requires-Dist: pytest>=7.0.0; extra == 'dev'
